LICENSE
MANIFEST.in
README.md
requirements.txt
setup.py
Flask_Captcha.egg-info/PKG-INFO
Flask_Captcha.egg-info/SOURCES.txt
Flask_Captcha.egg-info/dependency_links.txt
Flask_Captcha.egg-info/not-zip-safe
Flask_Captcha.egg-info/requires.txt
Flask_Captcha.egg-info/top_level.txt
flask_captcha/__init__.py
flask_captcha/helpers.py
flask_captcha/models.py
flask_captcha/settings.py
flask_captcha/views.py
flask_captcha/fonts/LICENSE
flask_captcha/fonts/Vera.ttf