Metadata-Version: 1.1
Name: Flask-Captcha
Version: 0.1.6
Summary: A very simple, yet powerful, Flask captcha extension
Home-page: https://github.com/agoraciudadana/flask-captcha
Author: Eduardo Robles Elvira
Author-email: edulix@wadobo.com
License: MIT
Platform: UNKNOWN
Classifier: Development Status :: 4 - Beta
Classifier: Environment :: Web Environment
Classifier: Intended Audience :: Developers
Classifier: License :: OSI Approved :: MIT License
Classifier: Operating System :: OS Independent
Classifier: Programming Language :: Python
Classifier: Topic :: Internet :: WWW/HTTP :: Dynamic Content
Classifier: Topic :: Software Development :: Libraries :: Python Modules
Classifier: Programming Language :: Python :: 2.6
Classifier: Programming Language :: Python :: 2.7
Classifier: Programming Language :: Python :: 3.3
Classifier: Topic :: Security
